pyabpoa.cpython-312-darwin.so
pyabpoa-1.5.2.dist-info/RECORD
pyabpoa-1.5.2.dist-info/LICENSE
pyabpoa-1.5.2.dist-info/WHEEL
pyabpoa-1.5.2.dist-info/top_level.txt
pyabpoa-1.5.2.dist-info/METADATA
