Metadata-Version: 2.1
Name: pyabpoa
Version: 1.5.2
Summary: pyabpoa: SIMD-based partial order alignment using adaptive band
Home-page: https://github.com/yangao07/abPOA
Author: Yan Gao
Author-email: yangao@ds.dfci.harvard.edu
License: MIT
Keywords: multiple-sequence-alignment  partial-order-graph-alignment
License-File: LICENSE
